olarm_api_rainepretorius/__init__.py
olarm_api_rainepretorius/const.py
olarm_api_rainepretorius/exceptions.py
olarm_api_rainepretorius-1.0.0.dist-info/LICENSE
olarm_api_rainepretorius-1.0.0.dist-info/METADATA
olarm_api_rainepretorius-1.0.0.dist-info/WHEEL
olarm_api_rainepretorius-1.0.0.dist-info/top_level.txt
olarm_api_rainepretorius-1.0.0.dist-info/RECORD
