Metadata-Version: 2.1
Name: olarm_api_rainepretorius
Version: 1.0.0
Summary: A package to interact with the Olarm API
Author-email: Raine Pretorius <raine.pretorius1@gmail.com>
Project-URL: Homepage, https://github.com/rainepretorius/olarm_python_package
Project-URL: Bug Tracker, https://github.com/rainepretorius/olarm_python_package/issues
Classifier: Programming Language :: Python :: 3
Classifier: License :: OSI Approved :: BSD License
Classifier: Operating System :: OS Independent
Requires-Python: >=3.11
License-File: LICENSE
